nosql_versioning/__init__.py
nosql_versioning-0.1.8.3.dist-info/DESCRIPTION.rst
nosql_versioning-0.1.8.3.dist-info/METADATA
nosql_versioning-0.1.8.3.dist-info/RECORD
nosql_versioning-0.1.8.3.dist-info/WHEEL
nosql_versioning-0.1.8.3.dist-info/metadata.json
nosql_versioning-0.1.8.3.dist-info/top_level.txt
tests/__init__.py
tests/context.py
tests/test_basic_example.py
tests/test_custom_decode.py
tests/test_custom_key.py
