Metadata-Version: 2.0
Name: nosql-versioning
Version: 0.1.8.3
Summary: Python Library for NoSQL database record versioning
Home-page: https://github.com/xinhuang/nosql_versioning
Author: Xin Huang
Author-email: xinhuang.abc@gmail.com
License: License :: OSI Approved :: MIT License
Platform: UNKNOWN
